ImageAI/DataProcessor.py
ImageAI/DatabaseHandler.py
ImageAI/__init__.py
tests/__init__.py
Simple_ImageAI-0.1.0.dist-info/METADATA
Simple_ImageAI-0.1.0.dist-info/WHEEL
Simple_ImageAI-0.1.0.dist-info/top_level.txt
Simple_ImageAI-0.1.0.dist-info/RECORD
